[
  {
    "title": "Project Work Day",
    "allDay": true,
    "start": "2020-01-24"
  },
  {
    "title": "Project Work Day",
    "allDay": true,
    "start": "2020-01-31"
  },
  {
    "title": "Project Work Day",
    "allDay": true,
    "start": "2020-02-11"
  },
  {
    "title": "WordPress: Project 4",
    "allDay": true,
    "start": "2020-02-21",
    "end": "2020-02-29"
  },
  {
    "title": "WordPress: Project 5",
    "allDay": true,
    "start": "2020-03-03",
    "end": "2020-03-07"
  },
  {
    "title": "Community Project Work",
    "allDay": true,
    "start": "2020-03-09",
    "end": "2020-03-27"
  },
  {
    "title": "Grad",
    "allDay": true,
    "start": "2020-03-27"
  },
  {
    "title": "Project 1 Check-in",
    "allDay": true,
    "start": "2020-10-11"
 },
 {
    "title": "Project 2 Check-in",
    "allDay": true,
    "start": "2020-10-18"
 },
 {
    "title": "Project 3 Check-in",
    "allDay": true,
    "start": "2020-10-25"
 },
 {
    "title": "Project 4 Check-in",
    "allDay": true,
    "start": "2020-11-08"
 },
 {
    "title": "Project 5 Check-in",
    "allDay": true,
    "start": "2020-11-22"
 }
]
